doko/__init__.py
doko/landmark.py
doko-0.4.0.dist-info/DESCRIPTION.rst
doko-0.4.0.dist-info/entry_points.txt
doko-0.4.0.dist-info/METADATA
doko-0.4.0.dist-info/metadata.json
doko-0.4.0.dist-info/RECORD
doko-0.4.0.dist-info/top_level.txt
doko-0.4.0.dist-info/WHEEL
