Metadata-Version: 2.0
Name: doko
Version: 0.4.0
Summary: Detect your current location.
Home-page: http://github.com/larsyencken/doko/
Author: Lars Yencken
Author-email: lars@yencken.org
License: ISC
Platform: UNKNOWN
Requires-Dist: PyYAML (==3.11)
Requires-Dist: geoip2 (>=0.5.1)
Requires-Dist: requests (>=2.2.1)
Provides-Extra: corelocation
Requires-Dist: pyobjc (>=2.4); extra == 'corelocation'
Requires-Dist: pyobjc-core (>=2.4); extra == 'corelocation'
Requires-Dist: pyobjc-framework-CoreLocation (>=2.4); extra == 'corelocation'
